hpelm/__init__.py
hpelm/elm.py
hpelm/hp_elm.py
hpelm/mss_cv.py
hpelm/mss_loo.py
hpelm/mss_v.py
hpelm/modules/__init__.py
hpelm/modules/hdf5_tools.py
hpelm/modules/mrsr.py
hpelm/modules/mrsr2.py
hpelm/modules/rbf_param.py
hpelm/nnets/__init__.py
hpelm/nnets/slfn.py
hpelm/nnets/slfn_python.py
hpelm/nnets/slfn_skcuda.py
hpelm/tests/__init__.py
hpelm/tests/test_acceptance.py
hpelm/tests/test_corr_hpelm.py
hpelm/tests/test_correctness.py
hpelm/tests/unittest_elm.py
hpelm/tests/unittest_hpelm.py
hpelm-1.0.9.data/scripts/elm_naive.py
hpelm-1.0.9.dist-info/METADATA
hpelm-1.0.9.dist-info/RECORD
hpelm-1.0.9.dist-info/WHEEL
hpelm-1.0.9.dist-info/top_level.txt
