Metadata-Version: 2.1
Name: hpelm
Version: 1.0.9
Summary: High-Performance implementation of an Extreme Learning Machine
Home-page: https://www.researchgate.net/profile/Anton_Akusok
Author: Anton Akusok
Author-email: akusok.a@gmail.com
License: BSD (3-clause)
Keywords: ELM HPC regression classification ANN
Platform: UNKNOWN
Classifier: Development Status :: 5 - Production/Stable
Classifier: Environment :: Console
Classifier: Intended Audience :: Science/Research
Classifier: License :: OSI Approved :: BSD License
Classifier: Natural Language :: English
Classifier: Operating System :: OS Independent
Classifier: Programming Language :: Python
Classifier: Topic :: Scientific/Engineering :: Information Analysis
Requires-Dist: numpy
Requires-Dist: scipy (>=0.12)
Requires-Dist: tables
Requires-Dist: fasteners
Requires-Dist: six
Requires-Dist: nose
